xrfeitoria/__init__.py
xrfeitoria/factory.py
xrfeitoria/version.py
xrfeitoria/actor/__init__.py
xrfeitoria/actor/actor_base.py
xrfeitoria/actor/actor_blender.py
xrfeitoria/actor/actor_unreal.py
xrfeitoria/camera/__init__.py
xrfeitoria/camera/camera_base.py
xrfeitoria/camera/camera_blender.py
xrfeitoria/camera/camera_parameter.py
xrfeitoria/camera/camera_unreal.py
xrfeitoria/cmd/__init__.py
xrfeitoria/cmd/blender/__init__.py
xrfeitoria/cmd/blender/install_plugin.py
xrfeitoria/cmd/blender/render.py
xrfeitoria/cmd/blender/vis_smplx.py
xrfeitoria/data_structure/__init__.py
xrfeitoria/data_structure/constants.py
xrfeitoria/data_structure/models.py
xrfeitoria/material/__init__.py
xrfeitoria/material/material_base.py
xrfeitoria/material/material_blender.py
xrfeitoria/material/material_unreal.py
xrfeitoria/object/__init__.py
xrfeitoria/object/object_base.py
xrfeitoria/object/object_utils.py
xrfeitoria/renderer/__init__.py
xrfeitoria/renderer/renderer_base.py
xrfeitoria/renderer/renderer_blender.py
xrfeitoria/renderer/renderer_unreal.py
xrfeitoria/rpc/__init__.py
xrfeitoria/rpc/client.py
xrfeitoria/rpc/exceptions.py
xrfeitoria/rpc/factory.py
xrfeitoria/rpc/validations.py
xrfeitoria/sequence/__init__.py
xrfeitoria/sequence/sequence_base.py
xrfeitoria/sequence/sequence_base.pyi
xrfeitoria/sequence/sequence_blender.py
xrfeitoria/sequence/sequence_blender.pyi
xrfeitoria/sequence/sequence_unreal.py
xrfeitoria/sequence/sequence_unreal.pyi
xrfeitoria/sequence/sequence_wrapper.py
xrfeitoria/sequence/sequence_wrapper.pyi
xrfeitoria/utils/__init__.py
xrfeitoria/utils/converter.py
xrfeitoria/utils/downloader.py
xrfeitoria/utils/plugin_infos.json
xrfeitoria/utils/projector.py
xrfeitoria/utils/publish_plugins.py
xrfeitoria/utils/runner.py
xrfeitoria/utils/setup.py
xrfeitoria/utils/tools.py
xrfeitoria/utils/validations.py
xrfeitoria/utils/viewer.py
xrfeitoria/utils/anim/__init__.py
xrfeitoria/utils/anim/constants.py
xrfeitoria/utils/anim/motion.py
xrfeitoria/utils/anim/transform3d.py
xrfeitoria-0.6.3.dist-info/LICENSE
xrfeitoria-0.6.3.dist-info/METADATA
xrfeitoria-0.6.3.dist-info/WHEEL
xrfeitoria-0.6.3.dist-info/entry_points.txt
xrfeitoria-0.6.3.dist-info/top_level.txt
xrfeitoria-0.6.3.dist-info/RECORD
