Metadata-Version: 2.1
Name: xrfeitoria
Version: 0.6.3
Summary: OpenXRLab Synthetic Data Rendering Toolbox
Author-email: OpenXRLab <openxrlab@pjlab.org.cn>
License: Apache License 2.0
Project-URL: Homepage, https://github.com/openxrlab/xrfeitoria
Project-URL: Bug Tracker, https://github.com/openxrlab/xrfeitoria/issues
Project-URL: Documentation, https://xrfeitoria.readthedocs.io/en/latest/
Classifier: Operating System :: Microsoft :: Windows
Classifier: Operating System :: Unix
Classifier: Operating System :: MacOS
Classifier: Operating System :: POSIX :: Linux
Classifier: Programming Language :: Python :: 3.8
Classifier: Programming Language :: Python :: 3.9
Classifier: Programming Language :: Python :: 3.10
Classifier: License :: OSI Approved :: Apache Software License
Requires-Python: <3.11,>=3.8
License-File: LICENSE
Requires-Dist: astunparse ==1.6.3
Requires-Dist: fake-bpy-module-latest
Requires-Dist: numpy <2,>=1
Requires-Dist: loguru <1
Requires-Dist: packaging <24,>=23
Requires-Dist: pydantic <3,>=2
Requires-Dist: psutil <6,>=5
Requires-Dist: rich <14,>=13
Requires-Dist: typer ==0.9.0
Requires-Dist: typing-extensions
Requires-Dist: xrprimer ==0.7.1
Provides-Extra: all
Requires-Dist: xrfeitoria[anim,doc,vis] ; extra == 'all'
Provides-Extra: anim
Requires-Dist: scipy <2,>1 ; extra == 'anim'
Provides-Extra: doc
Requires-Dist: autodoc-pydantic ==2.0.1 ; extra == 'doc'
Requires-Dist: docutils ; extra == 'doc'
Requires-Dist: ipykernel ; extra == 'doc'
Requires-Dist: ipywidgets ; extra == 'doc'
Requires-Dist: myst-parser ==2.0.0 ; extra == 'doc'
Requires-Dist: nbsphinx ==0.8.12 ; extra == 'doc'
Requires-Dist: sphinx ==7.2.5 ; extra == 'doc'
Requires-Dist: sphinx-copybutton ==0.5.2 ; extra == 'doc'
Requires-Dist: sphinx-gallery ==0.10.1 ; extra == 'doc'
Requires-Dist: sphinx-rtd-theme ==1.3.0 ; extra == 'doc'
Requires-Dist: sphinx-tabs ==3.4.1 ; extra == 'doc'
Requires-Dist: enum-tools[sphinx] ; extra == 'doc'
Provides-Extra: vis
Requires-Dist: matplotlib <4,>=3.4 ; extra == 'vis'
Requires-Dist: opencv-python <5,>=4 ; extra == 'vis'
Requires-Dist: flow-vis ==0.1 ; extra == 'vis'
